{
  "entityType" : "DASHBOARD",
  "entity" : {
    "assignedCustomers" : null,
    "configuration" : {
      "description" : ""
    },
    "customerId" : null,
    "externalId" : null,
    "id" : {
      "entityType" : "DASHBOARD",
      "id" : "41d85f00-4029-11ee-bb94-e90efb8ecc83"
    },
    "image" : null,
    "mobileHide" : false,
    "mobileOrder" : null,
    "name" : "Automezzi",
    "ownerId" : null,
    "title" : "Automezzi"
  },
  "relations" : [ ],
  "attributes" : {
    "SERVER_SCOPE" : [ ]
  }
}