{
  "entityType" : "ASSET",
  "entity" : {
    "additionalInfo" : {
      "description" : ""
    },
    "assetProfileId" : {
      "entityType" : "ASSET_PROFILE",
      "id" : "27c952c0-6109-11ef-b2e2-65b916afcec8"
    },
    "customerId" : {
      "entityType" : "CUSTOMER",
      "id" : "31750540-6108-11ef-b2e2-65b916afcec8"
    },
    "externalId" : null,
    "id" : {
      "entityType" : "ASSET",
      "id" : "83d0ed20-636c-11ef-b2e2-65b916afcec8"
    },
    "label" : null,
    "name" : "Family # 4",
    "ownerId" : {
      "entityType" : "CUSTOMER",
      "id" : "31750540-6108-11ef-b2e2-65b916afcec8"
    },
    "type" : "Family"
  },
  "relations" : [ ],
  "attributes" : {
    "SERVER_SCOPE" : [ ]
  }
}