{
  "entityType" : "DEVICE",
  "entity" : {
    "additionalInfo" : {
      "gateway" : false,
      "overwriteActivityTime" : false,
      "description" : ""
    },
    "customerId" : {
      "entityType" : "CUSTOMER",
      "id" : "13814000-1dd2-11b2-8080-808080808080"
    },
    "deviceData" : {
      "configuration" : {
        "type" : "DEFAULT"
      },
      "transportConfiguration" : {
        "type" : "DEFAULT"
      }
    },
    "deviceProfileId" : {
      "entityType" : "DEVICE_PROFILE",
      "id" : "7c20ce60-01d5-11ed-8014-35af6f7ed6b6"
    },
    "externalId" : null,
    "firmwareId" : null,
    "id" : {
      "entityType" : "DEVICE",
      "id" : "d7281f60-1c5a-11ef-b44e-91c31f727eb7"
    },
    "label" : "Armando",
    "name" : "armando",
    "ownerId" : null,
    "softwareId" : null,
    "type" : "default"
  },
  "credentials" : {
    "credentialsId" : "s46gNiA8BXqmZZzKaJSM",
    "credentialsType" : "ACCESS_TOKEN",
    "credentialsValue" : null
  },
  "attributes" : {
    "SERVER_SCOPE" : [ ],
    "SHARED_SCOPE" : [ ]
  }
}